aiodecorators/__init__.py
aiodecorators-0.2.1.dist-info/METADATA
aiodecorators-0.2.1.dist-info/WHEEL
aiodecorators-0.2.1.dist-info/top_level.txt
aiodecorators-0.2.1.dist-info/RECORD
