Metadata-Version: 2.1
Name: aiodecorators
Version: 0.2.1
Summary: Function decorators based on asyncio synchronization primitives
Home-page: http://github.com/dflupu/aiodecorators
Author: Daniel Lupu
Author-email: dflupu@gmail.com
License: MIT
Keywords: asyncio aio lock semaphore boundedsemaphore decorator decorators synchronization
